{
  "resource": "Users",
  "resource_explanation": null,
  "http_method": "POST",
  "route": "/users",
  "description": "Creating a new user",
  "explanation": "Create a new user",
  "parameters": [
    {
      "name": "user",
      "description": "user hash containing name, email, and password"
    }
  ],
  "response_fields": [

  ],
  "requests": [
    {
      "request_method": "POST",
      "request_path": "/users",
      "request_body": "user[name]=Whitley+Reichel&user[email]=zachery%40macejkovic.io&user[password]=BzCpUo3oUkCz",
      "request_headers": {
        "Host": "example.org",
        "Content-Type": "application/x-www-form-urlencoded",
        "Cookie": ""
      },
      "request_query_parameters": {
      },
      "request_content_type": "application/x-www-form-urlencoded",
      "response_status": 201,
      "response_status_text": "Created",
      "response_body": "{\n  \"name\": \"Whitley Reichel\",\n  \"email\": \"zachery@macejkovic.io\"\n}",
      "response_headers": {
        "Location": "http://example.org/api/v1/products/13",
        "Content-Type": "application/json; charset=utf-8",
        "ETag": "W/\"e538b4c9a4e5c22002cc634ce5d430de\"",
        "Cache-Control": "max-age=0, private, must-revalidate",
        "X-Request-Id": "c34d4af6-b920-4cd0-9f04-7cf22b871b20",
        "X-Runtime": "0.009272",
        "Content-Length": "58"
      },
      "response_content_type": "application/json; charset=utf-8",
      "curl": null
    }
  ]
}